boschshcpy/__init__.py
boschshcpy/api.py
boschshcpy/device.py
boschshcpy/device_helper.py
boschshcpy/device_service.py
boschshcpy/domain_impl.py
boschshcpy/emma.py
boschshcpy/exceptions.py
boschshcpy/generate_cert.py
boschshcpy/information.py
boschshcpy/message.py
boschshcpy/models_impl.py
boschshcpy/rawscan.py
boschshcpy/register_client.py
boschshcpy/room.py
boschshcpy/scenario.py
boschshcpy/services_impl.py
boschshcpy/session.py
boschshcpy/tls_ca_chain.pem
boschshcpy/userdefinedstate.py
boschshcpy-0.2.106.dist-info/LICENSE
boschshcpy-0.2.106.dist-info/METADATA
boschshcpy-0.2.106.dist-info/WHEEL
boschshcpy-0.2.106.dist-info/entry_points.txt
boschshcpy-0.2.106.dist-info/top_level.txt
boschshcpy-0.2.106.dist-info/RECORD
