Metadata-Version: 2.1
Name: boschshcpy
Version: 0.2.106
Summary: Bosch Smart Home Controller API Python Library
Home-page: https://github.com/tschamm/boschshcpy
Author: Clemens-Alexander Brust, Thomas Schamm
Author-email: cabrust@pm.me, thomas@tschamm.de
License: bsd-3-clause
Project-URL: Bug Reports, https://github.com/tschamm/boschshcpy/issues
Project-URL: Source, https://github.com/tschamm/boschshcpy
Keywords: boschshcpy
Classifier: Intended Audience :: Developers
Classifier: Operating System :: OS Independent
Classifier: Programming Language :: Python
Classifier: Programming Language :: Python :: 3
Classifier: License :: OSI Approved :: BSD License
Requires-Python: >=3.10, <4
License-File: LICENSE
Requires-Dist: cryptography>=3.3.2
Requires-Dist: getmac<1,>=0.8.2
Requires-Dist: requests>=2.22
Requires-Dist: zeroconf>=0.28.0
